async_garlandtools-0.0.2.dist-info/licenses/LICENSE
garlandtools/__init__.py
garlandtools/_enums.py
garlandtools/_types.py
garlandtools/errors.py
garlandtools/modules.py
async_garlandtools-0.0.2.dist-info/METADATA
async_garlandtools-0.0.2.dist-info/WHEEL
async_garlandtools-0.0.2.dist-info/top_level.txt
async_garlandtools-0.0.2.dist-info/RECORD
