Metadata-Version: 2.4
Name: async_garlandtools
Version: 0.0.2
Author-email: k8thekat <Cadwalladerkatelynn@gmail.com>
License: MIT License
Project-URL: GitHub, https://github.com/k8thekat/GarlandToolsAPI_wrapper
Classifier: Development Status :: 5 - Production/Stable
Classifier: Intended Audience :: Developers
Classifier: License :: OSI Approved :: GNU General Public License v3 or later (GPLv3+)
Classifier: Operating System :: OS Independent
Classifier: Programming Language :: Python :: 3.12
Classifier: Framework :: AsyncIO
Classifier: Topic :: Internet
Classifier: Topic :: Software Development :: Libraries
Classifier: Topic :: Software Development :: Libraries :: Python Modules
Classifier: Topic :: Utilities
Classifier: Typing :: Typed
Requires-Python: >=3.12.0
License-File: LICENSE
Requires-Dist: aiohttp>=3.12.13
Requires-Dist: aiohttp-client-cache>=0.13.0
Requires-Dist: aiosqlite>=0.21.0
Dynamic: license-file
